[
  {
    "id": "aorist-sigmatic",
    "title": "Аорист: сигматический (с -σ-)",
    "category": "verbs",
    "tags": ["aorist", "past", "endings", "stress"],
    "summary": "Простое законченное прошедшее. Перфективный стем + -σ + окончания -α/-ες/-ε/-αμε/-ατε/-αν. Ударение всегда на третьем слоге от конца, при необходимости добавляется ε-приращение.",
    "blocks": [
      { "type": "p", "text": "Аорист — простое законченное прошедшее: «написал», «купил», «полюбил». Большинство глаголов из наших карточек образуют его сигматически — с появлением буквы -σ- между основой и личным окончанием." },
      { "type": "p", "text": "Перфективный стем у разных классов получается по-своему: γράφ-ω → γράψ-, αγοράζ-ω → αγόρασ-, αγαπά-ω → αγαπή-σ-, ακού-ω → άκου-σ-." },
      { "type": "list", "items": [
        "1 ед.: -α   — έγραψα",
        "2 ед.: -ες  — έγραψες",
        "3 ед.: -ε   — έγραψε",
        "1 мн.: -αμε — γράψαμε",
        "2 мн.: -ατε — γράψατε",
        "3 мн.: -αν  — έγραψαν"
      ]},
      { "type": "examples", "items": [
        { "gr": "γράφω → έγραψα",    "ru": "пишу → я написал" },
        { "gr": "αγοράζω → αγόρασα", "ru": "покупаю → я купил" },
        { "gr": "αγαπάω → αγάπησα",  "ru": "люблю → я полюбил" },
        { "gr": "ακούω → άκουσα",    "ru": "слышу → я услышал" }
      ]},
      { "type": "p", "text": "Ударение всегда падает на третий слог от конца. Если основа короткая и трёх слогов не получается (γράψ-α — всего два), добавляется ε-приращение: έ-γραψ-α. В формах 1 и 2 мн. лица слово удлиняется за счёт окончания, и приращение уже не нужно: γράψαμε, γράψατε." }
    ],
    "related_verbs": ["agorazo", "akoyo", "agapao"]
  },
  {
    "id": "future-tha",
    "title": "Будущее время с θα",
    "category": "verbs",
    "tags": ["future", "tha", "endings"],
    "summary": "θα + перфективный стем (как у аориста) + окончания настоящего времени -ω/-εις/-ει/-ουμε/-ετε/-ουν. Без ε-приращения.",
    "blocks": [
      { "type": "p", "text": "Простое будущее в новогреческом строится с частицей θα перед глаголом. Это самое употребительное будущее, обозначает однократное законченное действие: «я куплю», «он напишет»." },
      { "type": "p", "text": "Стем — тот же перфективный, что в аористе (γράψ-, αγόρασ-, αγαπή-σ-, άκου-σ-), а окончания берём из настоящего времени: -ω / -εις / -ει / -ουμε / -ετε / -ουν." },
      { "type": "list", "items": [
        "1 ед.: θα -ω    — θα γράψω",
        "2 ед.: θα -εις  — θα γράψεις",
        "3 ед.: θα -ει   — θα γράψει",
        "1 мн.: θα -ουμε — θα γράψουμε",
        "2 мн.: θα -ετε  — θα γράψετε",
        "3 мн.: θα -ουν  — θα γράψουν"
      ]},
      { "type": "examples", "items": [
        { "gr": "γράφω → θα γράψω",     "ru": "пишу → я напишу" },
        { "gr": "αγοράζω → θα αγοράσω", "ru": "покупаю → я куплю" },
        { "gr": "αγαπάω → θα αγαπήσω",  "ru": "люблю → я полюблю" },
        { "gr": "ακούω → θα ακούσω",    "ru": "слышу → я услышу" }
      ]},
      { "type": "p", "text": "В отличие от аориста, ε-приращение здесь не нужно: формы будущего сами по себе достаточно длинные, и ударение естественно ложится в пределах последних трёх слогов." }
    ],
    "related_rules": ["aorist-sigmatic"],
    "related_verbs": ["agorazo", "akoyo", "agapao"]
  },
  {
    "id": "adjectives-comparison-pio",
    "title": "Степени сравнения прилагательных: πιο",
    "category": "adjectives",
    "tags": ["adjectives", "comparison", "comparative", "superlative", "pio", "articles"],
    "summary": "Сравнительная степень — πιο + прилагательное + από; превосходная — артикль ο/η/το + πιο + прилагательное + από όλους/όλες/όλα. Прилагательное согласуется с подлежащим в роде и числе.",
    "blocks": [
      { "type": "p", "text": "В новогреческом сравнительную и превосходную степени проще всего строить аналитически — со словом πιο («более»). Положительная степень — это обычное прилагательное, согласованное с подлежащим в роде и числе." },
      { "type": "p", "text": "Сравнительная степень: πιο ставится перед прилагательным, а объект сравнения вводится предлогом από. Само прилагательное окончания не меняет и продолжает согласовываться с подлежащим." },
      { "type": "p", "text": "Превосходная степень: к πιο + прилагательному добавляется определённый артикль (ο, η или το) того же рода, что и подлежащее. Группа сравнения вводится оборотом από όλους / από όλες / από όλα — в зависимости от рода тех, с кем сравнивают." },
      { "type": "list", "items": [
        "м.р.: μικρός → πιο μικρός → ο πιο μικρός (από όλους)",
        "ж.р.: μικρή → πιο μικρή → η πιο μικρή (από όλες)",
        "ср.р.: μικρό → πιο μικρό → το πιο μικρό (από όλα)"
      ]},
      { "type": "examples", "items": [
        { "gr": "Ο Σπύρος είναι μικρός.",                       "ru": "Спирос маленький." },
        { "gr": "Ο Πέτρος είναι πιο μικρός από τον Σπύρο.",      "ru": "Петрос меньше, чем Спирос." },
        { "gr": "Ο Νίκος είναι ο πιο μικρός από όλους.",         "ru": "Никос — самый маленький из всех." },
        { "gr": "Η Έλλη είναι η πιο μικρή από όλες.",            "ru": "Элли — самая маленькая из всех." },
        { "gr": "Το σπίτι σου είναι πιο μικρό από το σπίτι μου.", "ru": "Твой дом меньше моего дома." },
        { "gr": "Το σπίτι του είναι το πιο μικρό από όλα.",       "ru": "Его дом — самый маленький из всех." }
      ]}
    ],
    "related_rules": ["adjectives-comparison-teros", "adjectives-comparison-irregular"]
  },
  {
    "id": "adjectives-comparison-teros",
    "title": "Степени сравнения прилагательных: суффикс -τερος",
    "category": "adjectives",
    "tags": ["adjectives", "comparison", "comparative", "superlative", "teros", "endings", "articles"],
    "summary": "Альтернативная сравнительная степень: к основе прилагательного добавляется суффикс -τερος (μικρός → μικρότερος). Превосходная — с артиклем (ο μικρότερος). К длинным прилагательным эта форма не присоединяется — для них только аналитическая форма с πιο.",
    "blocks": [
      { "type": "p", "text": "Помимо аналитической формы с πιο, в новогреческом есть вторая, синтетическая форма сравнительной степени — с суффиксом -τερος, который присоединяется к основе прилагательного. Для коротких прилагательных обе формы равноценны и взаимозаменяемы: πιο μικρός = μικρότερος." },
      { "type": "p", "text": "Превосходная степень от синтетической формы строится так же, как и от аналитической: перед прилагательным ставится определённый артикль (ο, η, το) того же рода, что и подлежащее, а группа сравнения вводится оборотом από όλους / από όλες / από όλα." },
      { "type": "p", "text": "Важное ограничение: суффикс -τερος не присоединяется к длинным прилагательным. Например, у αφηρημένος («рассеянный») формы вроде αφηρημενότερος не употребляются, поэтому в таких случаях остаётся только аналитический способ — πιο αφηρημένος / ο πιο αφηρημένος." },
      { "type": "examples", "items": [
        { "gr": "Ο Κώστας είναι πιο μικρός από τον Γιάννη.",       "ru": "Костас меньше Янниса." },
        { "gr": "Ο Κώστας είναι μικρότερος από τον Γιάννη.",       "ru": "Костас меньше Янниса (то же, синтетическая форма)." },
        { "gr": "Ο Κώστας είναι ο πιο μικρός από όλους.",          "ru": "Костас — самый маленький из всех." },
        { "gr": "Ο Κώστας είναι ο μικρότερος από όλους.",          "ru": "Костас — самый маленький из всех (то же, синтетическая форма)." },
        { "gr": "Ο Κώστας είναι πιο αφηρημένος από τον Γιάννη.",   "ru": "Костас более рассеянный, чем Яннис." },
        { "gr": "Ο Κώστας είναι ο πιο αφηρημένος από όλους μας.",  "ru": "Костас — самый рассеянный из всех нас." }
      ]}
    ],
    "related_rules": ["adjectives-comparison-pio", "adjectives-comparison-irregular"]
  },
  {
    "id": "adjectives-comparison-irregular",
    "title": "Неправильные степени сравнения прилагательных",
    "category": "adjectives",
    "tags": ["adjectives", "comparison", "comparative", "superlative", "irregular"],
    "summary": "Несколько базовых прилагательных образуют сравнительную и превосходную степени не по общему правилу: формы нужно запомнить — καλός → καλύτερος, μεγάλος → μεγαλύτερος, άσχημος/κακός → χειρότερος, πολύς → περισσότερος.",
    "blocks": [
      { "type": "p", "text": "Часть базовых прилагательных образует сравнительную степень с особенностями: либо с изменением основы (καλός → καλύτερος, μεγάλος → μεγαλύτερος), либо вовсе с другой основой (άσχημος / κακός → χειρότερος, πολύς → περισσότερος). Эти формы — исключения и просто запоминаются." },
      { "type": "p", "text": "Превосходная степень у таких прилагательных образуется по общему правилу — добавлением определённого артикля (ο, η, το) того же рода, что и подлежащее: ο καλύτερος, ο μεγαλύτερος, ο χειρότερος, ο περισσότερος." },
      { "type": "list", "items": [
        "καλός (хороший)              → καλύτερος       → ο καλύτερος",
        "μεγάλος (большой)            → μεγαλύτερος     → ο μεγαλύτερος",
        "άσχημος / κακός (плохой)     → χειρότερος      → ο χειρότερος",
        "πολύς (многий)               → περισσότερος    → ο περισσότερος"
      ]},
      { "type": "p", "text": "Особенность пары άσχημος / κακός: у обоих прилагательных одна и та же сравнительная форма — χειρότερος, и одна и та же превосходная — ο χειρότερος." },
      { "type": "examples", "items": [
        { "gr": "καλός → καλύτερος → ο καλύτερος",          "ru": "хороший → лучше → самый лучший" },
        { "gr": "καλή → καλύτερη → η καλύτερη",             "ru": "хорошая → лучше → самая лучшая (та же модель в женском роде)" },
        { "gr": "μεγάλος → μεγαλύτερος → ο μεγαλύτερος",    "ru": "большой → больше → самый большой" },
        { "gr": "άσχημος → χειρότερος → ο χειρότερος",       "ru": "некрасивый → хуже → самый худший" },
        { "gr": "κακός → χειρότερος → ο χειρότερος",         "ru": "плохой → хуже → самый плохой" },
        { "gr": "πολύς → περισσότερος → ο περισσότερος",     "ru": "многий → больший → наибольший" }
      ]}
    ],
    "related_rules": ["adjectives-comparison-pio", "adjectives-comparison-teros"]
  },
  {
    "id": "indefinite-words-negation-affirmation",
    "title": "Неопределённые слова в вопросе, отрицании и утверждении",
    "category": "syntax",
    "tags": ["negation", "affirmation", "indefinite", "pronouns", "adverbs"],
    "summary": "В вопросах и отрицательных предложениях используются формы типа τίποτα, κανένας, καθόλου, πουθενά, ποτέ. В утвердительных предложениях им соответствуют κάτι, κάποιος, λίγο/πολύ, κάπου, πάντα, καμιά φορά, κάποτε.",
    "blocks": [
      {
        "type": "p",
        "text": "В новогреческом неопределённые местоимения и наречия часто выбираются по типу предложения. В вопросах и отрицании употребляется один набор слов, а в утверждении — другой."
      },
      {
        "type": "p",
        "text": "Формы τίποτα, κανένας-καμία-κανένα, καθόλου, πουθενά, ποτέ характерны для вопроса и отрицания. В утверждении обычно используются положительные соответствия: κάτι, κάποιος-κάποια-κάποιο, λίγο, πολύ, κάπου, πάντα, καμιά φορά, κάποτε."
      },
      {
        "type": "list",
        "items": [
          "τίποτα → κάτι",
          "κανένας-καμία-κανένα → κάποιος-κάποια-κάποιο κ.λπ.",
          "καθόλου → λίγο, πολύ",
          "πουθενά → κάπου",
          "ποτέ → πάντα, καμιά φορά, κάποτε κ.λπ."
        ]
      },
      {
        "type": "examples",
        "items": [
          { "gr": "τίποτα → κάτι", "ru": "ничего / что-нибудь → что-то" },
          { "gr": "κανένας-καμία-κανένα → κάποιος-κάποια-κάποιο", "ru": "никто / кто-нибудь → кто-то" },
          { "gr": "καθόλου → λίγο, πολύ", "ru": "совсем не / нисколько → немного, много" },
          { "gr": "πουθενά → κάπου", "ru": "нигде / куда-нибудь → где-то / куда-то" },
          { "gr": "ποτέ → πάντα, καμιά φορά, κάποτε", "ru": "никогда / когда-нибудь → всегда, иногда, когда-то" }
        ]
      }
    ]
  }
,
{
  "id": "indefinite-cards-tipota-kati",
  "title": "Карточки: τίποτα / κάτι",
  "category": "syntax",
  "tags": [
    "negation",
    "affirmation",
    "question",
    "indefinite",
    "cards",
    "tipota-kati"
  ],
  "summary": "Пара τίποτα / κάτι тренируется через отрицание, вопрос и утверждение. В отрицании τίποτα значит «ничего», в вопросе — «что-нибудь», а в утверждении κάτι значит «что-то».",
  "blocks": [
    {
      "type": "p",
      "text": "Эта пара меняет перевод в зависимости от типа предложения. В отрицании используется τίποτα, в вопросе тоже τίποτα, а в утверждении — κάτι."
    },
    {
      "type": "list",
      "items": [
        "отрицание: τίποτα — ничего",
        "вопрос: τίποτα; — что-нибудь?",
        "утверждение: κάτι — что-то"
      ]
    },
    {
      "type": "examples",
      "items": [
        {
          "gr": "Δεν είδα τίποτα.",
          "ru": "Я ничего не видел."
        },
        {
          "gr": "Είδες τίποτα;",
          "ru": "Ты что-нибудь видел?"
        },
        {
          "gr": "Είδα κάτι.",
          "ru": "Я что-то видел."
        }
      ]
    }
  ],
  "related_rules": [
    "indefinite-words-negation-affirmation"
  ]
},
{
  "id": "indefinite-cards-kanenas-kapoios",
  "title": "Карточки: κανένας / κάποιος",
  "category": "syntax",
  "tags": [
    "negation",
    "affirmation",
    "question",
    "indefinite",
    "pronouns",
    "cards",
    "kanenas-kapoios"
  ],
  "summary": "Формы κανένας / καμία / κανένα используются в отрицании и вопросе, а κάποιος / κάποια / κάποιο — в утверждении. Значение зависит от контекста: «никто / никакой», «кто-нибудь / какой-нибудь» или «кто-то / какой-то».",
  "blocks": [
    {
      "type": "p",
      "text": "Эта группа важна из-за рода: κανένας / κάποιος — мужской род, καμία / κάποια — женский, κανένα / κάποιο — средний. В отрицании и вопросе используется форма с καν-, в утверждении — форма с κάποι-."
    },
    {
      "type": "list",
      "items": [
        "отрицание: κανένας / καμία / κανένα — никто; никакой / никакая / никакое",
        "вопрос: κανένας / καμία / κανένα; — кто-нибудь? какой-нибудь? какая-нибудь? какое-нибудь?",
        "утверждение: κάποιος / κάποια / κάποιο — кто-то; какой-то / какая-то / какое-то"
      ]
    },
    {
      "type": "examples",
      "items": [
        {
          "gr": "Δεν ήρθε κανένας.",
          "ru": "Никто не пришёл."
        },
        {
          "gr": "Δεν έχω κανένα φίλο εδώ.",
          "ru": "У меня здесь нет никакого друга."
        },
        {
          "gr": "Δεν είδα καμία ταινία αυτή την εβδομάδα.",
          "ru": "Я не посмотрел никакого фильма на этой неделе."
        },
        {
          "gr": "Ήρθε κανένας;",
          "ru": "Кто-нибудь пришёл?"
        },
        {
          "gr": "Ήρθε κάποιος.",
          "ru": "Кто-то пришёл."
        },
        {
          "gr": "Κάποια κοπέλα σε περιμένει έξω.",
          "ru": "Какая-то девушка ждёт тебя снаружи."
        }
      ]
    }
  ],
  "related_rules": [
    "indefinite-words-negation-affirmation"
  ]
},
{
  "id": "indefinite-cards-katholou-ligo-poly",
  "title": "Карточки: καθόλου / λίγο / πολύ",
  "category": "syntax",
  "tags": [
    "negation",
    "affirmation",
    "question",
    "indefinite",
    "adverbs",
    "cards",
    "katholou-ligo-poly"
  ],
  "summary": "Καθόλου используется в отрицании как «совсем не» и в вопросе как «хоть чуть-чуть?». В утверждении вместо него используются λίγο или πολύ.",
  "blocks": [
    {
      "type": "p",
      "text": "Καθόλου обычно связано с отрицанием или вопросом. В утвердительном предложении для количества используются λίγο или πολύ."
    },
    {
      "type": "list",
      "items": [
        "отрицание: καθόλου — совсем не",
        "вопрос: καθόλου; — хоть чуть-чуть?",
        "утверждение: λίγο / πολύ — немного / много"
      ]
    },
    {
      "type": "examples",
      "items": [
        {
          "gr": "Δεν έχω καθόλου χρόνο.",
          "ru": "У меня совсем нет времени."
        },
        {
          "gr": "Έχεις καθόλου χρόνο;",
          "ru": "У тебя есть хоть немного времени?"
        },
        {
          "gr": "Έχω λίγο χρόνο.",
          "ru": "У меня есть немного времени."
        }
      ]
    }
  ],
  "related_rules": [
    "indefinite-words-negation-affirmation"
  ]
},
{
  "id": "indefinite-cards-pouthena-kapou",
  "title": "Карточки: πουθενά / κάπου",
  "category": "syntax",
  "tags": [
    "negation",
    "affirmation",
    "question",
    "indefinite",
    "adverbs",
    "cards",
    "pouthena-kapou"
  ],
  "summary": "Πουθενά используется в отрицании как «нигде / никуда» и в вопросе как «где-нибудь / куда-нибудь?». В утверждении ему соответствует κάπου — «где-то / куда-то».",
  "blocks": [
    {
      "type": "p",
      "text": "Эта пара тренирует направление и место. В отрицании и вопросе используется πουθενά, а в утверждении — κάπου."
    },
    {
      "type": "list",
      "items": [
        "отрицание: πουθενά — нигде / никуда",
        "вопрос: πουθενά; — где-нибудь? / куда-нибудь?",
        "утверждение: κάπου — где-то / куда-то"
      ]
    },
    {
      "type": "examples",
      "items": [
        {
          "gr": "Δεν πήγα πουθενά.",
          "ru": "Я никуда не ходил."
        },
        {
          "gr": "Πήγες πουθενά το σαββατοκύριακο;",
          "ru": "Ты куда-нибудь ходил на выходных?"
        },
        {
          "gr": "Ήμουν κάπου.",
          "ru": "Я где-то был."
        },
        {
          "gr": "Πήγα κάπου.",
          "ru": "Я куда-то ходил."
        }
      ]
    }
  ],
  "related_rules": [
    "indefinite-words-negation-affirmation"
  ]
},
{
  "id": "indefinite-cards-pote-panta-kamia-fora-kapote",
  "title": "Карточки: ποτέ / πάντα / καμιά φορά / κάποτε",
  "category": "syntax",
  "tags": [
    "negation",
    "affirmation",
    "question",
    "indefinite",
    "adverbs",
    "cards",
    "pote-panta-kamia-fora-kapote"
  ],
  "summary": "Ποτέ используется в отрицании как «никогда» и в вопросе как «когда-нибудь?». В утверждении используются πάντα, καμιά φορά или κάποτε.",
  "blocks": [
    {
      "type": "p",
      "text": "Ποτέ в отрицании даёт значение «никогда», а в вопросе — «когда-нибудь?». В утверждении выбирается положительное слово времени: πάντα, καμιά φορά или κάποτε."
    },
    {
      "type": "list",
      "items": [
        "отрицание: ποτέ — никогда",
        "вопрос: ποτέ; — когда-нибудь?",
        "утверждение: πάντα — всегда",
        "утверждение: καμιά φορά — иногда",
        "утверждение: κάποτε — когда-то"
      ]
    },
    {
      "type": "examples",
      "items": [
        {
          "gr": "Δεν πάω ποτέ στο θέατρο.",
          "ru": "Я никогда не хожу в театр."
        },
        {
          "gr": "Πας ποτέ στο θέατρο;",
          "ru": "Ты когда-нибудь ходишь в театр?"
        },
        {
          "gr": "Πάω στο θέατρο πάντα.",
          "ru": "Я всегда хожу в театр."
        }
      ]
    }
  ],
  "related_rules": [
    "indefinite-words-negation-affirmation"
  ]
}
]